{
  "type": "minecraft:crafting_shapeless",
  "category": "misc",
  "group": "netherite_ingot",
  "ingredients": [
    {
      "item": "minecraft:netherite_scrap"
    },
    {
      "item": "minecraft:netherite_scrap"
    },
    {
      "item": "minecraft:netherite_scrap"
    },
    {
      "item": "minecraft:netherite_scrap"
    },
    {
      "item": "dmlreloaded:glitch_infused_ingot"
    },
    {
      "item": "dmlreloaded:glitch_infused_ingot"
    },
    {
      "item": "dmlreloaded:glitch_infused_ingot"
    },
    {
      "item": "dmlreloaded:glitch_infused_ingot"
    }
  ],
  "result": {
    "item": "dmlreloaded:netherite_glitch_infused_ingot"
  }
}