{
  "parent": "minecraft:recipes/root",
  "rewards": {
    "recipes": [
      "minecraft:ender_stone_from_living_matter_extraterrestrial"
    ]
  },
  "criteria": {
    "has_item": {
      "trigger": "minecraft:inventory_changed",
      "conditions": {
        "items": [
          {
            "items": [
              "dmlreloaded:living_matter_extraterrestrial"
            ]
          }
        ]
      }
    },
    "has_the_recipe": {
      "trigger": "minecraft:recipe_unlocked",
      "conditions": {
        "recipe": "minecraft:ender_stone_from_living_matter_extraterrestrial"
      }
    }
  },
  "requirements": [
    [
      "has_item",
      "has_the_recipe"
    ]
  ]
}